nimblephysics_libs/.DS_Store
nimblephysics_libs/_nimblephysics.pyi
nimblephysics_libs/__init__.py
nimblephysics_libs/py.typed
nimblephysics_libs/_nimblephysics.so
nimblephysics_libs/dynamics/__init__.pyi
nimblephysics_libs/exo/__init__.pyi
nimblephysics_libs/simulation/__init__.pyi
nimblephysics_libs/server/__init__.pyi
nimblephysics_libs/utils/.DS_Store
nimblephysics_libs/utils/__init__.pyi
nimblephysics_libs/utils/StringUtils/__init__.pyi
nimblephysics_libs/utils/UniversalLoader/__init__.pyi
nimblephysics_libs/utils/SkelParser/__init__.pyi
nimblephysics_libs/utils/SdfParser/__init__.pyi
nimblephysics_libs/math/__init__.pyi
nimblephysics_libs/realtime/__init__.pyi
nimblephysics_libs/common/__init__.pyi
nimblephysics_libs/trajectory/__init__.pyi
nimblephysics_libs/biomechanics/.DS_Store
nimblephysics_libs/biomechanics/__init__.pyi
nimblephysics_libs/biomechanics/OpenSimParser/__init__.pyi
nimblephysics_libs/performance/__init__.pyi
nimblephysics_libs/neural/__init__.pyi
nimblephysics_libs/constraint/__init__.pyi
nimblephysics_libs/collision/__init__.pyi
nimblephysics/bullet_renderer.py
nimblephysics/marker_mocap.py
nimblephysics/__init__.py
nimblephysics/get_anthropometric_log_pdf.py
nimblephysics/get_marker_dist_to_nearest_vertex.py
nimblephysics/get_lowest_point.py
nimblephysics/loader.py
nimblephysics/motion_dynamics_dataset.py
nimblephysics/get_height.py
nimblephysics/mapping.py
nimblephysics/gui_server.py
nimblephysics/native_trajectory_support.py
nimblephysics/timestep.py
nimblephysics/models/rajagopal.py
nimblephysics/models/__init__.py
nimblephysics/models/rajagopal_data/Rajagopal2015.osim
nimblephysics/models/rajagopal_data/ANSUR_II_MALE_Public.csv
nimblephysics/models/rajagopal_data/ANSUR_II_FEMALE_Public.csv
nimblephysics/models/rajagopal_data/ANSUR_Rajagopal_metrics.xml
nimblephysics/models/rajagopal_data/Geometry/thumb_proximal_lvs.vtp.ply
nimblephysics/models/rajagopal_data/Geometry/l_bofoot.vtp.ply
nimblephysics-0.10.52.2.dist-info/RECORD
nimblephysics-0.10.52.2.dist-info/LICENSE
nimblephysics-0.10.52.2.dist-info/WHEEL
nimblephysics-0.10.52.2.dist-info/top_level.txt
nimblephysics-0.10.52.2.dist-info/METADATA
