Metadata-Version: 2.1
Name: nimblephysics
Version: 0.10.52.2
Summary: A differentiable fully featured physics engine
Author: Keenon Werling
Author-email: keenonwerling@gmail.com
License: MIT
License-File: LICENSE
Requires-Dist: torch
Requires-Dist: numpy
